{
  "elevation": {
    "solid": {
      "0": {
        "value": "{color.solid.dark.5}",
        "type": "color"
      },
      "1": {
        "value": "{color.solid.dark.10}",
        "type": "color"
      },
      "2": {
        "value": "{color.solid.dark.20}",
        "type": "color"
      },
      "3": {
        "value": "{color.solid.dark.40}",
        "type": "color"
      },
      "4": {
        "value": "{color.solid.dark.50}",
        "type": "color"
      },
      "5": {
        "value": "{color.solid.dark.60}",
        "type": "color"
      },
      "6": {
        "value": "{color.solid.dark.70}",
        "type": "color"
      },
      "7": {
        "value": "{color.solid.dark.100}",
        "type": "color"
      }
    },
    "alpha": {
      "0": {
        "value": "{color.alpha.dark.5}",
        "type": "color"
      },
      "1": {
        "value": "{color.alpha.dark.10}",
        "type": "color"
      },
      "2": {
        "value": "{color.alpha.dark.20}",
        "type": "color"
      },
      "3": {
        "value": "{color.alpha.dark.30}",
        "type": "color"
      },
      "4": {
        "value": "{color.alpha.dark.30}",
        "type": "color"
      },
      "5": {
        "value": "{color.alpha.dark.60}",
        "type": "color"
      },
      "6": {
        "value": "{color.alpha.dark.70}",
        "type": "color"
      },
      "7": {
        "value": "{color.alpha.dark.100}",
        "type": "color"
      }
    }
  },
  "on-surface": {
    "inverse": {
      "value": "{elevation.solid.1}",
      "type": "color"
    },
    "seconday": {
      "value": "{elevation.solid.6}",
      "type": "color"
    },
    "tertiary": {
      "value": "{elevation.solid.3}",
      "type": "color"
    },
    "primary": {
      "value": "{elevation.solid.7}",
      "type": "color"
    },
    "on-dark": {
      "value": "{elevation.solid.7}",
      "type": "color"
    },
    "on-light": {
      "value": "{elevation.solid.0}",
      "type": "color"
    }
  },
  "status": {
    "critical": {
      "value": "{color.hues.red}",
      "type": "color"
    }
  }
}